ca_ez_manager/__init__.py
ca_ez_manager/__main__.py
ca_ez_manager/cli.py
ca_ez_manager/constants.py
ca_ez_manager/crypto_utils.py
ca_ez_manager/actions/ca.py
ca_ez_manager/actions/cert.py
ca_ez_manager-0.0.3.dist-info/LICENSE
ca_ez_manager-0.0.3.dist-info/METADATA
ca_ez_manager-0.0.3.dist-info/WHEEL
ca_ez_manager-0.0.3.dist-info/entry_points.txt
ca_ez_manager-0.0.3.dist-info/top_level.txt
ca_ez_manager-0.0.3.dist-info/RECORD
