Metadata-Version: 2.1
Name: ca-ez-manager
Version: 0.0.3
Summary: CLI tool to simply manage Certification Authorities using the shell
Author: Riccardo Tornesello
License: MIT License
Project-URL: Homepage, https://github.com/riccardotornesello/ca-ez-manager
Project-URL: Issues, https://github.com/riccardotornesello/ca-ez-manager/issues
Requires-Python: >=3.8
License-File: LICENSE
Requires-Dist: cryptography ==42.0.5
Requires-Dist: inquirerpy ==0.3.4
Requires-Dist: rich ==13.7.1
Requires-Dist: typer ==0.12.1
